MANIFEST.in
README.rst
setup.cfg
setup.py
syfilebrowser/__init__.py
syfilebrowser/base.py
syfilebrowser/decorators.py
syfilebrowser/fields.py
syfilebrowser/forms.py
syfilebrowser/functions.py
syfilebrowser/models.py
syfilebrowser/settings.py
syfilebrowser/storage.py
syfilebrowser/urls.py
syfilebrowser/views.py
syfilebrowser.egg-info/PKG-INFO
syfilebrowser.egg-info/SOURCES.txt
syfilebrowser.egg-info/dependency_links.txt
syfilebrowser.egg-info/not-zip-safe
syfilebrowser.egg-info/top_level.txt
syfilebrowser/locale/zh_CN/LC_MESSAGES/django.mo
syfilebrowser/locale/zh_CN/LC_MESSAGES/django.po
syfilebrowser/locale/zh_TW/LC_MESSAGES/django.mo
syfilebrowser/locale/zh_TW/LC_MESSAGES/django.po
syfilebrowser/static/syfilebrowser/css/rtl.css
syfilebrowser/static/syfilebrowser/css/syfilebrowser.css
syfilebrowser/static/syfilebrowser/img/syfilebrowser_icon_delete.gif
syfilebrowser/static/syfilebrowser/img/syfilebrowser_icon_delete_hover.gif
syfilebrowser/static/syfilebrowser/img/syfilebrowser_icon_rename.gif
syfilebrowser/static/syfilebrowser/img/syfilebrowser_icon_rename_hover.gif
syfilebrowser/static/syfilebrowser/img/syfilebrowser_icon_select.gif
syfilebrowser/static/syfilebrowser/img/syfilebrowser_icon_select_disabled.gif
syfilebrowser/static/syfilebrowser/img/syfilebrowser_icon_select_hover.gif
syfilebrowser/static/syfilebrowser/img/syfilebrowser_icon_show.gif
syfilebrowser/static/syfilebrowser/img/syfilebrowser_icon_show_hover.gif
syfilebrowser/static/syfilebrowser/img/syfilebrowser_icon_showversions_hover.gif
syfilebrowser/static/syfilebrowser/img/syfilebrowser_type_.gif
syfilebrowser/static/syfilebrowser/img/syfilebrowser_type_audio.gif
syfilebrowser/static/syfilebrowser/img/syfilebrowser_type_code.gif
syfilebrowser/static/syfilebrowser/img/syfilebrowser_type_document.gif
syfilebrowser/static/syfilebrowser/img/syfilebrowser_type_folder.gif
syfilebrowser/static/syfilebrowser/img/syfilebrowser_type_image.gif
syfilebrowser/static/syfilebrowser/img/syfilebrowser_type_video.gif
syfilebrowser/static/syfilebrowser/js/AddSyFileBrowser.js
syfilebrowser/static/syfilebrowser/js/FB_CKEditor.js
syfilebrowser/static/syfilebrowser/js/FB_FileBrowseField.js
