Metadata-Version: 1.0
Name: syfilebrowser
Version: 1.0
Summary: a dependency for the ShuyuCMS.
Home-page: http://zhidaoii.com
Author: Feichi Long
Author-email: feichi@longfeichi.com
License: UNKNOWN
Platform: UNKNOWN
